{
  "cases": {
    "brown_v_board": {
      "id": "brown_v_board",
      "title": "Brown v. Board of Education",
      "court": "Supreme Court of the United States",
      "date": "May 17, 1954",
      "jurisdiction": "United States",
      "concepts": [
        "constitutional_law",
        "civil_rights",
        "equal_protection"
      ],
      "citations": [
        "Plessy v. Ferguson"
      ],
      "bbesEncoding": "⠠⠃⠗⠕⠺⠝ ⠧ ⠠⠃⠕⠁⠗⠙ ⠕⠋ ⠠⠑⠙⠥⠉⠁⠞⠊⠕⠝ ⠕⠋ ⠠⠞⠕⠏⠑⠅⠁ ⠼⠉⠙⠛ ⠠⠥⠠⠎ ⠼⠙⠓⠉ ⠼⠁⠊⠑⠙ ⠺⠁⠎ ⠁ ⠇⠁⠝⠙⠍⠁⠗⠅ ⠙⠑⠉⠊⠎⠊⠕⠝ ⠕⠋ ⠞⠓⠑ ⠠⠥⠠⠎ ⠠⠎⠥⠏⠗⠑⠍⠑ ⠠⠉⠕⠥⠗⠞ ⠊⠝ ⠺⠓⠊⠉⠓ ⠞⠓⠑ ⠠⠉⠕⠥⠗⠞ ⠗⠥⠇⠑⠙ ⠞⠓⠁⠞ ⠠⠥⠠⠎ ⠎⠞⠁⠞⠑ ⠇⠁⠺⠎ ⠑⠎⠞⠁⠃⠇⠊⠎⠓⠊⠝⠛ ⠗⠁⠉⠊⠁⠇ ⠎⠑⠛⠗⠑⠛⠁⠞⠊⠕⠝ ⠊⠝ ⠏⠥⠃⠇⠊⠉ ⠎⠉⠓⠕⠕⠇⠎ ⠁⠗⠑ ⠥⠝⠉⠕⠝⠎⠞⠊⠞⠥⠞⠊⠕⠝⠁⠇ ⠑⠧⠑⠝ ⠊⠋ ⠞⠓⠑ ⠎⠑⠛⠗⠑⠛⠁⠞⠑⠙ ⠎⠉⠓⠕⠕⠇⠎ ⠁⠗⠑ ⠕⠞⠓⠑⠗⠺⠊⠎⠑ ⠑⠟⠥⠁⠇ ⠊⠝ ⠟⠥⠁⠇⠊⠞⠽ ⠠⠞⠓⠑ ⠙⠑⠉⠊⠎⠊⠕⠝ ⠕⠧⠑⠗⠞⠥⠗⠝⠑⠙ ⠞⠓⠑ ⠠⠏⠇⠑⠎⠎⠽ ⠧ ⠠⠋⠑⠗⠛⠥⠎⠕⠝ ⠙⠑⠉⠊⠎⠊⠕⠝ ⠕⠋ ⠼⠁⠓⠊⠋ ⠺⠓⠊⠉⠓ ⠓⠁⠙ ⠁⠇⠇⠕⠺⠑⠙ ⠎⠞⠁⠞⠑⠎⠏⠕⠝⠎⠕⠗⠑⠙ ⠎⠑⠛⠗⠑⠛⠁⠞⠊⠕⠝ ⠊⠝ ⠏⠥⠃⠇⠊⠉ ⠑⠙⠥⠉⠁⠞⠊⠕⠝ ⠠⠞⠓⠑ ⠠⠉⠕⠥⠗⠞⠎ ⠥⠝⠁⠝⠊⠍⠕⠥⠎ ⠙⠑⠉⠊⠎⠊⠕⠝ ⠎⠞⠁⠞⠑⠙ ⠞⠓⠁⠞ ⠎⠑⠏⠁⠗⠁⠞⠑ ⠑⠙⠥⠉⠁⠞⠊⠕⠝⠁⠇ ⠋⠁⠉⠊⠇⠊⠞⠊⠑⠎ ⠁⠗⠑ ⠊⠝⠓⠑⠗⠑⠝⠞⠇⠽ ⠥⠝⠑⠟⠥⠁⠇ ⠁⠝⠙ ⠞⠓⠑⠗⠑⠋⠕⠗⠑ ⠧⠊⠕⠇⠁⠞⠑ ⠞⠓⠑ ⠠⠑⠟⠥⠁⠇ ⠠⠏⠗⠕⠞⠑⠉⠞⠊⠕⠝ ⠠⠉⠇⠁⠥⠎⠑ ⠕⠋ ⠞⠓⠑ ⠠⠋⠕⠥⠗⠞⠑⠑⠝⠞⠓ ⠠⠁⠍⠑⠝⠙⠍⠑⠝⠞ ⠕⠋ ⠞⠓⠑ ⠠⠥⠠⠎ ⠠⠉⠕⠝⠎⠞⠊⠞⠥⠞⠊⠕⠝⠠⠞⠓⠑ ⠉⠁⠎⠑ ⠕⠗⠊⠛⠊⠝⠁⠞⠑⠙ ⠊⠝ ⠼⠁⠊⠑⠁ ⠺⠓⠑⠝ ⠞⠓⠑ ⠏⠥⠃⠇⠊⠉ ⠎⠉⠓⠕⠕⠇ ⠙⠊⠎⠞⠗⠊⠉⠞ ⠊⠝ ⠠⠞⠕⠏⠑⠅⠁ ⠠⠅⠁⠝⠎⠁⠎ ⠗⠑⠋⠥⠎⠑⠙ ⠞⠕ ⠑⠝⠗⠕⠇⠇ ⠇⠕⠉⠁⠇ ⠃⠇⠁⠉⠅ ⠗⠑⠎⠊⠙⠑⠝⠞ ⠠⠕⠇⠊⠧⠑⠗ ⠠⠃⠗⠕⠺⠝⠎ ⠙⠁⠥⠛⠓⠞⠑⠗ ⠁⠞ ⠞⠓⠑ ⠎⠉⠓⠕⠕⠇ ⠉⠇⠕⠎⠑⠎⠞ ⠞⠕ ⠞⠓⠑⠊⠗ ⠓⠕⠍⠑ ⠊⠝⠎⠞⠑⠁⠙ ⠗⠑⠟⠥⠊⠗⠊⠝⠛ ⠓⠑⠗ ⠞⠕ ⠗⠊⠙⠑ ⠁ ⠃⠥⠎ ⠞⠕ ⠁ ⠎⠑⠛⠗⠑⠛⠁⠞⠑⠙ ⠃⠇⠁⠉⠅ ⠑⠇⠑⠍⠑⠝⠞⠁⠗⠽ ⠎⠉⠓⠕⠕⠇ ⠋⠁⠗⠞⠓⠑⠗ ⠁⠺⠁⠽ ⠠⠞⠓⠑ ⠠⠃⠗⠕⠺⠝⠎ ⠁⠝⠙ ⠞⠺⠑⠇⠧⠑ ⠕⠞⠓⠑⠗ ⠇⠕⠉⠁⠇ ⠃⠇⠁⠉⠅ ⠋⠁⠍⠊⠇⠊⠑⠎ ⠊⠝ ⠎⠊⠍⠊⠇⠁⠗ ⠎⠊⠞⠥⠁⠞⠊⠕⠝⠎ ⠞⠓⠑⠝ ⠋⠊⠇⠑⠙ ⠁ ⠉⠇⠁⠎⠎ ⠁⠉⠞⠊⠕⠝ ⠇⠁⠺⠎⠥⠊⠞ ⠊⠝ ⠠⠥⠠⠎ ⠋⠑⠙⠑⠗⠁⠇ ⠉⠕⠥⠗⠞ ⠁⠛⠁⠊⠝⠎⠞ ⠞⠓⠑ ⠠⠞⠕⠏⠑⠅⠁ ⠠⠃⠕⠁⠗⠙ ⠕⠋ ⠠⠑⠙⠥⠉⠁⠞⠊⠕⠝ ⠁⠇⠇⠑⠛⠊⠝⠛ ⠞⠓⠁⠞ ⠊⠞⠎ ⠎⠑⠛⠗⠑⠛⠁⠞⠊⠕⠝ ⠏⠕⠇⠊⠉⠽ ⠺⠁⠎ ⠥⠝⠉⠕⠝⠎⠞⠊⠞⠥⠞⠊⠕⠝⠁⠇ ⠠⠁ ⠞⠓⠗⠑⠑⠚⠥⠙⠛⠑ ⠏⠁⠝⠑⠇ ⠕⠋ ⠞⠓⠑ ⠠⠥⠠⠎ ⠠⠙⠊⠎⠞⠗⠊⠉⠞ ⠠⠉⠕⠥⠗⠞ ⠋⠕⠗ ⠞⠓⠑ ⠠⠙⠊⠎⠞⠗⠊⠉⠞ ⠕⠋ ⠠⠅⠁⠝⠎⠁⠎ ⠗⠑⠝⠙⠑⠗⠑⠙ ⠁ ⠧⠑⠗⠙⠊⠉⠞ ⠁⠛⠁⠊⠝⠎⠞ ⠞⠓⠑ ⠠⠃⠗⠕⠺⠝⠎ ⠗⠑⠇⠽⠊⠝⠛ ⠕⠝ ⠞⠓⠑ ⠏⠗⠑⠉⠑⠙⠑⠝⠞ ⠕⠋ ⠞⠓⠑ ⠠⠎⠥⠏⠗⠑⠍⠑ ⠠⠉⠕⠥⠗⠞⠎ ⠙⠑⠉⠊⠎⠊⠕⠝ ⠊⠝ ⠠⠏⠇⠑⠎⠎⠽ ⠧ ⠠⠋⠑⠗⠛⠥⠎⠕⠝ ⠼⠁⠓⠊⠋ ⠺⠓⠊⠉⠓ ⠓⠁⠙ ⠥⠏⠓⠑⠇⠙ ⠁ ⠎⠞⠁⠞⠑ ⠇⠁⠺ ⠗⠑⠟⠥⠊⠗⠊⠝⠛ ⠎⠑⠏⠁⠗⠁⠞⠑ ⠃⠥⠞ ⠑⠟⠥⠁⠇ ⠎⠑⠛⠗⠑⠛⠁⠞⠑⠙ ⠋⠁⠉⠊⠇⠊⠞⠊⠑⠎ ⠋⠕⠗ ⠃⠇⠁⠉⠅⠎ ⠁⠝⠙ ⠺⠓⠊⠞⠑⠎ ⠊⠝ ⠗⠁⠊⠇⠺⠁⠽ ⠉⠁⠗⠎ ⠠⠞⠓⠑ ⠠⠃⠗⠕⠺⠝⠎ ⠞⠓⠑⠝ ⠗⠑⠏⠗⠑⠎⠑⠝⠞⠑⠙ ⠃⠽ ⠨⠠⠝⠁⠁⠉⠏ ⠉⠓⠊⠑⠋ ⠉⠕⠥⠝⠎⠑⠇ ⠠⠞⠓⠥⠗⠛⠕⠕⠙ ⠠⠍⠁⠗⠎⠓⠁⠇⠇ ⠁⠏⠏⠑⠁⠇⠑⠙ ⠞⠕ ⠞⠓⠑ ⠠⠎⠥⠏⠗⠑⠍⠑ ⠠⠉⠕⠥⠗⠞ ⠺⠓⠊⠉⠓ ⠉⠕⠝⠎⠕⠇⠊⠙⠁⠞⠑⠙ ⠞⠓⠑⠊⠗ ⠉⠁⠎⠑ ⠺⠊⠞⠓ ⠕⠞⠓⠑⠗ ⠎⠊⠍⠊⠇⠁⠗ ⠎⠑⠛⠗⠑⠛⠁⠞⠊⠕⠝ ⠉⠁⠎⠑⠎ ⠊⠝⠞⠕ ⠠⠃⠗⠕⠺⠝ ⠧ ⠠⠃⠕⠁⠗⠙ ⠕⠋ ⠠⠑⠙⠥⠉⠁⠞⠊⠕⠝",
      "compressed": {
        "compressed": "11111111",
        "metadata": {
          "originalSize": 13200,
          "compressedSize": 8,
          "compressionRatio": 0.0006060606060606061,
          "compressionPercentage": "99.94%",
          "processingTime": "0.14ms",
          "conceptCount": 1,
          "encodingType": "semantic"
        },
        "compressionMap": {
          "STRING": "11111111"
        }
      },
      "path": "/home/owner/CascadeProjects/braille/data/legal/cases/brown_v_board.json"
    },
    "miranda_v_arizona": {
      "id": "miranda_v_arizona",
      "title": "Miranda v. Arizona",
      "court": "Supreme Court of the United States",
      "date": "June 13, 1966",
      "jurisdiction": "United States",
      "concepts": [
        "constitutional_law",
        "criminal_law",
        "procedural_law",
        "fifth_amendment"
      ],
      "citations": [
        "Escobedo v. Illinois",
        "Gideon v. Wainwright"
      ],
      "bbesEncoding": "⠠⠍⠊⠗⠁⠝⠙⠁ ⠧ ⠠⠁⠗⠊⠵⠕⠝⠁ ⠼⠉⠓⠙ ⠠⠥⠠⠎ ⠼⠙⠉⠋ ⠼⠁⠊⠋⠋ ⠺⠁⠎ ⠁ ⠇⠁⠝⠙⠍⠁⠗⠅ ⠙⠑⠉⠊⠎⠊⠕⠝ ⠕⠋ ⠞⠓⠑ ⠠⠥⠠⠎ ⠠⠎⠥⠏⠗⠑⠍⠑ ⠠⠉⠕⠥⠗⠞ ⠊⠝ ⠺⠓⠊⠉⠓ ⠞⠓⠑ ⠠⠉⠕⠥⠗⠞ ⠗⠥⠇⠑⠙ ⠞⠓⠁⠞ ⠞⠓⠑ ⠠⠋⠊⠋⠞⠓ ⠠⠁⠍⠑⠝⠙⠍⠑⠝⠞ ⠞⠕ ⠞⠓⠑ ⠠⠥⠠⠎ ⠠⠉⠕⠝⠎⠞⠊⠞⠥⠞⠊⠕⠝ ⠗⠑⠎⠞⠗⠊⠉⠞⠎ ⠏⠗⠕⠎⠑⠉⠥⠞⠕⠗⠎ ⠋⠗⠕⠍ ⠥⠎⠊⠝⠛ ⠁ ⠏⠑⠗⠎⠕⠝⠎ ⠎⠞⠁⠞⠑⠍⠑⠝⠞⠎ ⠍⠁⠙⠑ ⠊⠝ ⠗⠑⠎⠏⠕⠝⠎⠑ ⠞⠕ ⠊⠝⠞⠑⠗⠗⠕⠛⠁⠞⠊⠕⠝ ⠊⠝ ⠏⠕⠇⠊⠉⠑ ⠉⠥⠎⠞⠕⠙⠽ ⠁⠎ ⠑⠧⠊⠙⠑⠝⠉⠑ ⠁⠞ ⠞⠓⠑⠊⠗ ⠞⠗⠊⠁⠇ ⠥⠝⠇⠑⠎⠎ ⠞⠓⠑⠽ ⠉⠁⠝ ⠎⠓⠕⠺ ⠞⠓⠁⠞ ⠞⠓⠑ ⠏⠑⠗⠎⠕⠝ ⠺⠁⠎ ⠊⠝⠋⠕⠗⠍⠑⠙ ⠕⠋ ⠞⠓⠑ ⠗⠊⠛⠓⠞ ⠞⠕ ⠉⠕⠝⠎⠥⠇⠞ ⠺⠊⠞⠓ ⠁⠝ ⠁⠞⠞⠕⠗⠝⠑⠽ ⠃⠑⠋⠕⠗⠑ ⠁⠝⠙ ⠙⠥⠗⠊⠝⠛ ⠟⠥⠑⠎⠞⠊⠕⠝⠊⠝⠛ ⠁⠝⠙ ⠕⠋ ⠞⠓⠑ ⠗⠊⠛⠓⠞ ⠁⠛⠁⠊⠝⠎⠞ ⠎⠑⠇⠋⠊⠝⠉⠗⠊⠍⠊⠝⠁⠞⠊⠕⠝ ⠃⠑⠋⠕⠗⠑ ⠏⠕⠇⠊⠉⠑ ⠟⠥⠑⠎⠞⠊⠕⠝⠊⠝⠛ ⠁⠝⠙ ⠞⠓⠁⠞ ⠞⠓⠑ ⠙⠑⠋⠑⠝⠙⠁⠝⠞ ⠝⠕⠞ ⠕⠝⠇⠽ ⠥⠝⠙⠑⠗⠎⠞⠕⠕⠙ ⠞⠓⠑⠎⠑ ⠗⠊⠛⠓⠞⠎ ⠃⠥⠞ ⠧⠕⠇⠥⠝⠞⠁⠗⠊⠇⠽ ⠺⠁⠊⠧⠑⠙ ⠞⠓⠑⠍⠠⠞⠓⠑ ⠉⠁⠎⠑ ⠃⠑⠛⠁⠝ ⠺⠊⠞⠓ ⠞⠓⠑ ⠼⠁⠊⠋⠉ ⠁⠗⠗⠑⠎⠞ ⠕⠋ ⠠⠑⠗⠝⠑⠎⠞⠕ ⠠⠍⠊⠗⠁⠝⠙⠁ ⠺⠓⠕ ⠺⠁⠎ ⠉⠓⠁⠗⠛⠑⠙ ⠺⠊⠞⠓ ⠗⠁⠏⠑ ⠅⠊⠙⠝⠁⠏⠏⠊⠝⠛ ⠁⠝⠙ ⠗⠕⠃⠃⠑⠗⠽ ⠠⠍⠊⠗⠁⠝⠙⠁ ⠺⠁⠎ ⠝⠕⠞ ⠊⠝⠋⠕⠗⠍⠑⠙ ⠕⠋ ⠓⠊⠎ ⠗⠊⠛⠓⠞⠎ ⠏⠗⠊⠕⠗ ⠞⠕ ⠞⠓⠑ ⠏⠕⠇⠊⠉⠑ ⠊⠝⠞⠑⠗⠗⠕⠛⠁⠞⠊⠕⠝ ⠠⠙⠥⠗⠊⠝⠛ ⠞⠓⠑ ⠞⠺⠕⠓⠕⠥⠗ ⠊⠝⠞⠑⠗⠗⠕⠛⠁⠞⠊⠕⠝ ⠠⠍⠊⠗⠁⠝⠙⠁ ⠁⠇⠇⠑⠛⠑⠙⠇⠽ ⠉⠕⠝⠋⠑⠎⠎⠑⠙ ⠞⠕ ⠉⠕⠍⠍⠊⠞⠞⠊⠝⠛ ⠞⠓⠑ ⠉⠗⠊⠍⠑⠎ ⠺⠓⠊⠉⠓ ⠞⠓⠑ ⠏⠕⠇⠊⠉⠑ ⠁⠏⠏⠁⠗⠑⠝⠞⠇⠽ ⠗⠑⠉⠕⠗⠙⠑⠙ ⠠⠍⠊⠗⠁⠝⠙⠁ ⠺⠁⠎ ⠞⠓⠑⠝ ⠉⠕⠝⠧⠊⠉⠞⠑⠙ ⠕⠋ ⠃⠕⠞⠓ ⠗⠁⠏⠑ ⠁⠝⠙ ⠅⠊⠙⠝⠁⠏⠏⠊⠝⠛ ⠁⠝⠙ ⠎⠑⠝⠞⠑⠝⠉⠑⠙ ⠞⠕ ⠼⠃⠚ ⠞⠕ ⠼⠉⠚ ⠽⠑⠁⠗⠎ ⠊⠝ ⠏⠗⠊⠎⠕⠝ ⠠⠓⠑ ⠁⠏⠏⠑⠁⠇⠑⠙ ⠞⠕ ⠞⠓⠑ ⠠⠁⠗⠊⠵⠕⠝⠁ ⠠⠎⠥⠏⠗⠑⠍⠑ ⠠⠉⠕⠥⠗⠞ ⠉⠇⠁⠊⠍⠊⠝⠛ ⠞⠓⠁⠞ ⠞⠓⠑ ⠏⠕⠇⠊⠉⠑ ⠓⠁⠙ ⠥⠝⠉⠕⠝⠎⠞⠊⠞⠥⠞⠊⠕⠝⠁⠇⠇⠽ ⠕⠃⠞⠁⠊⠝⠑⠙ ⠓⠊⠎ ⠉⠕⠝⠋⠑⠎⠎⠊⠕⠝⠠⠞⠓⠑ ⠠⠎⠥⠏⠗⠑⠍⠑ ⠠⠉⠕⠥⠗⠞ ⠊⠝ ⠁ ⠼⠑⠼⠙ ⠙⠑⠉⠊⠎⠊⠕⠝ ⠺⠗⠊⠞⠞⠑⠝ ⠃⠽ ⠠⠉⠓⠊⠑⠋ ⠠⠚⠥⠎⠞⠊⠉⠑ ⠠⠑⠁⠗⠇ ⠠⠺⠁⠗⠗⠑⠝ ⠗⠥⠇⠑⠙ ⠞⠓⠁⠞ ⠞⠓⠑ ⠏⠗⠕⠎⠑⠉⠥⠞⠊⠕⠝ ⠉⠕⠥⠇⠙ ⠝⠕⠞ ⠊⠝⠞⠗⠕⠙⠥⠉⠑ ⠠⠍⠊⠗⠁⠝⠙⠁⠎ ⠉⠕⠝⠋⠑⠎⠎⠊⠕⠝ ⠁⠎ ⠑⠧⠊⠙⠑⠝⠉⠑ ⠊⠝ ⠁ ⠉⠗⠊⠍⠊⠝⠁⠇ ⠞⠗⠊⠁⠇ ⠃⠑⠉⠁⠥⠎⠑ ⠞⠓⠑ ⠏⠕⠇⠊⠉⠑ ⠓⠁⠙ ⠋⠁⠊⠇⠑⠙ ⠞⠕ ⠋⠊⠗⠎⠞ ⠊⠝⠋⠕⠗⠍ ⠠⠍⠊⠗⠁⠝⠙⠁ ⠕⠋ ⠓⠊⠎ ⠗⠊⠛⠓⠞ ⠞⠕ ⠁⠝ ⠁⠞⠞⠕⠗⠝⠑⠽ ⠁⠝⠙ ⠁⠛⠁⠊⠝⠎⠞ ⠎⠑⠇⠋⠊⠝⠉⠗⠊⠍⠊⠝⠁⠞⠊⠕⠝ ⠠⠞⠓⠑ ⠠⠎⠥⠏⠗⠑⠍⠑ ⠠⠉⠕⠥⠗⠞ ⠙⠊⠙ ⠝⠕⠞ ⠎⠏⠑⠉⠊⠋⠽ ⠞⠓⠑ ⠑⠭⠁⠉⠞ ⠺⠕⠗⠙⠊⠝⠛ ⠞⠕ ⠥⠎⠑ ⠺⠓⠑⠝ ⠊⠝⠋⠕⠗⠍⠊⠝⠛ ⠁ ⠎⠥⠎⠏⠑⠉⠞ ⠕⠋ ⠞⠓⠑⠊⠗ ⠗⠊⠛⠓⠞⠎ ⠠⠓⠕⠺⠑⠧⠑⠗ ⠞⠓⠑ ⠠⠉⠕⠥⠗⠞ ⠙⠊⠙ ⠉⠗⠑⠁⠞⠑ ⠁ ⠎⠑⠞ ⠕⠋ ⠛⠥⠊⠙⠑⠇⠊⠝⠑⠎ ⠞⠓⠁⠞ ⠍⠥⠎⠞ ⠃⠑ ⠋⠕⠇⠇⠕⠺⠑⠙ ⠠⠞⠓⠑ ⠗⠥⠇⠊⠝⠛ ⠺⠁⠎ ⠇⠁⠞⠑⠗ ⠺⠑⠁⠅⠑⠝⠑⠙ ⠃⠽ ⠎⠑⠧⠑⠗⠁⠇ ⠕⠧⠑⠗⠗⠊⠙⠊⠝⠛ ⠙⠑⠉⠊⠎⠊⠕⠝⠎",
      "compressed": {
        "compressed": "11111111",
        "metadata": {
          "originalSize": 13064,
          "compressedSize": 8,
          "compressionRatio": 0.000612369871402327,
          "compressionPercentage": "99.94%",
          "processingTime": "0.02ms",
          "conceptCount": 1,
          "encodingType": "semantic"
        },
        "compressionMap": {
          "STRING": "11111111"
        }
      },
      "path": "/home/owner/CascadeProjects/braille/data/legal/cases/miranda_v_arizona.json"
    },
    "roe_v_wade": {
      "id": "roe_v_wade",
      "title": "Roe v. Wade",
      "court": "Supreme Court of the United States",
      "date": "January 22, 1973",
      "jurisdiction": "United States",
      "concepts": [
        "constitutional_law",
        "privacy",
        "due_process"
      ],
      "citations": [
        "Griswold v. Connecticut",
        "Doe v. Bolton"
      ],
      "bbesEncoding": "⠠⠗⠕⠑ ⠧ ⠠⠺⠁⠙⠑ ⠼⠙⠁⠚ ⠠⠥⠠⠎ ⠼⠁⠁⠉ ⠼⠁⠊⠛⠉ ⠺⠁⠎ ⠁ ⠇⠁⠝⠙⠍⠁⠗⠅ ⠙⠑⠉⠊⠎⠊⠕⠝ ⠕⠋ ⠞⠓⠑ ⠠⠥⠠⠎ ⠠⠎⠥⠏⠗⠑⠍⠑ ⠠⠉⠕⠥⠗⠞ ⠊⠝ ⠺⠓⠊⠉⠓ ⠞⠓⠑ ⠠⠉⠕⠥⠗⠞ ⠗⠥⠇⠑⠙ ⠞⠓⠁⠞ ⠞⠓⠑ ⠠⠉⠕⠝⠎⠞⠊⠞⠥⠞⠊⠕⠝ ⠕⠋ ⠞⠓⠑ ⠠⠥⠝⠊⠞⠑⠙ ⠠⠎⠞⠁⠞⠑⠎ ⠛⠑⠝⠑⠗⠁⠇⠇⠽ ⠏⠗⠕⠞⠑⠉⠞⠎ ⠁ ⠏⠗⠑⠛⠝⠁⠝⠞ ⠺⠕⠍⠁⠝⠎ ⠇⠊⠃⠑⠗⠞⠽ ⠞⠕ ⠉⠓⠕⠕⠎⠑ ⠞⠕ ⠓⠁⠧⠑ ⠁⠝ ⠁⠃⠕⠗⠞⠊⠕⠝ ⠠⠞⠓⠑ ⠙⠑⠉⠊⠎⠊⠕⠝ ⠎⠞⠗⠥⠉⠅ ⠙⠕⠺⠝ ⠍⠁⠝⠽ ⠋⠑⠙⠑⠗⠁⠇ ⠁⠝⠙ ⠎⠞⠁⠞⠑ ⠁⠃⠕⠗⠞⠊⠕⠝ ⠇⠁⠺⠎ ⠁⠝⠙ ⠉⠁⠥⠎⠑⠙ ⠁⠝ ⠕⠝⠛⠕⠊⠝⠛ ⠁⠃⠕⠗⠞⠊⠕⠝ ⠙⠑⠃⠁⠞⠑ ⠊⠝ ⠞⠓⠑ ⠠⠥⠝⠊⠞⠑⠙ ⠠⠎⠞⠁⠞⠑⠎ ⠁⠃⠕⠥⠞ ⠺⠓⠑⠞⠓⠑⠗ ⠕⠗ ⠞⠕ ⠺⠓⠁⠞ ⠑⠭⠞⠑⠝⠞ ⠁⠃⠕⠗⠞⠊⠕⠝ ⠎⠓⠕⠥⠇⠙ ⠃⠑ ⠇⠑⠛⠁⠇ ⠺⠓⠕ ⠎⠓⠕⠥⠇⠙ ⠙⠑⠉⠊⠙⠑ ⠞⠓⠑ ⠇⠑⠛⠁⠇⠊⠞⠽ ⠕⠋ ⠁⠃⠕⠗⠞⠊⠕⠝ ⠁⠝⠙ ⠺⠓⠁⠞ ⠞⠓⠑ ⠗⠕⠇⠑ ⠕⠋ ⠍⠕⠗⠁⠇ ⠁⠝⠙ ⠗⠑⠇⠊⠛⠊⠕⠥⠎ ⠧⠊⠑⠺⠎ ⠊⠝ ⠞⠓⠑ ⠏⠕⠇⠊⠞⠊⠉⠁⠇ ⠎⠏⠓⠑⠗⠑ ⠎⠓⠕⠥⠇⠙ ⠃⠑ ⠠⠞⠓⠑ ⠙⠑⠉⠊⠎⠊⠕⠝ ⠁⠇⠎⠕ ⠎⠓⠁⠏⠑⠙ ⠙⠑⠃⠁⠞⠑ ⠉⠕⠝⠉⠑⠗⠝⠊⠝⠛ ⠺⠓⠊⠉⠓ ⠍⠑⠞⠓⠕⠙⠎ ⠞⠓⠑ ⠠⠎⠥⠏⠗⠑⠍⠑ ⠠⠉⠕⠥⠗⠞ ⠎⠓⠕⠥⠇⠙ ⠥⠎⠑ ⠊⠝ ⠉⠕⠝⠎⠞⠊⠞⠥⠞⠊⠕⠝⠁⠇ ⠁⠙⠚⠥⠙⠊⠉⠁⠞⠊⠕⠝⠠⠞⠓⠑ ⠉⠁⠎⠑ ⠺⠁⠎ ⠃⠗⠕⠥⠛⠓⠞ ⠃⠽ ⠠⠝⠕⠗⠍⠁ ⠠⠍⠉⠠⠉⠕⠗⠧⠑⠽⠅⠝⠕⠺⠝ ⠃⠽ ⠞⠓⠑ ⠇⠑⠛⠁⠇ ⠏⠎⠑⠥⠙⠕⠝⠽⠍ ⠠⠚⠁⠝⠑ ⠠⠗⠕⠑⠺⠓⠕ ⠊⠝ ⠼⠁⠊⠋⠊ ⠃⠑⠉⠁⠍⠑ ⠏⠗⠑⠛⠝⠁⠝⠞ ⠺⠊⠞⠓ ⠓⠑⠗ ⠞⠓⠊⠗⠙ ⠉⠓⠊⠇⠙ ⠠⠍⠉⠠⠉⠕⠗⠧⠑⠽ ⠺⠁⠝⠞⠑⠙ ⠁⠝ ⠁⠃⠕⠗⠞⠊⠕⠝ ⠃⠥⠞ ⠇⠊⠧⠑⠙ ⠊⠝ ⠠⠞⠑⠭⠁⠎ ⠺⠓⠑⠗⠑ ⠁⠃⠕⠗⠞⠊⠕⠝ ⠺⠁⠎ ⠊⠇⠇⠑⠛⠁⠇ ⠑⠭⠉⠑⠏⠞ ⠺⠓⠑⠝ ⠝⠑⠉⠑⠎⠎⠁⠗⠽ ⠞⠕ ⠎⠁⠧⠑ ⠞⠓⠑ ⠍⠕⠞⠓⠑⠗⠎ ⠇⠊⠋⠑ ⠠⠓⠑⠗ ⠁⠞⠞⠕⠗⠝⠑⠽⠎ ⠠⠎⠁⠗⠁⠓ ⠠⠺⠑⠙⠙⠊⠝⠛⠞⠕⠝ ⠁⠝⠙ ⠠⠇⠊⠝⠙⠁ ⠠⠉⠕⠋⠋⠑⠑ ⠋⠊⠇⠑⠙ ⠁ ⠇⠁⠺⠎⠥⠊⠞ ⠕⠝ ⠓⠑⠗ ⠃⠑⠓⠁⠇⠋ ⠊⠝ ⠠⠥⠠⠎ ⠋⠑⠙⠑⠗⠁⠇ ⠉⠕⠥⠗⠞ ⠁⠛⠁⠊⠝⠎⠞ ⠓⠑⠗ ⠇⠕⠉⠁⠇ ⠙⠊⠎⠞⠗⠊⠉⠞ ⠁⠞⠞⠕⠗⠝⠑⠽ ⠠⠓⠑⠝⠗⠽ ⠠⠺⠁⠙⠑ ⠁⠇⠇⠑⠛⠊⠝⠛ ⠞⠓⠁⠞ ⠠⠞⠑⠭⠁⠎⠎ ⠁⠃⠕⠗⠞⠊⠕⠝ ⠇⠁⠺⠎ ⠺⠑⠗⠑ ⠥⠝⠉⠕⠝⠎⠞⠊⠞⠥⠞⠊⠕⠝⠁⠇ ⠠⠁ ⠎⠏⠑⠉⠊⠁⠇ ⠞⠓⠗⠑⠑⠚⠥⠙⠛⠑ ⠏⠁⠝⠑⠇ ⠕⠋ ⠞⠓⠑ ⠠⠥⠠⠎ ⠠⠙⠊⠎⠞⠗⠊⠉⠞ ⠠⠉⠕⠥⠗⠞ ⠋⠕⠗ ⠞⠓⠑ ⠠⠝⠕⠗⠞⠓⠑⠗⠝ ⠠⠙⠊⠎⠞⠗⠊⠉⠞ ⠕⠋ ⠠⠞⠑⠭⠁⠎ ⠓⠑⠁⠗⠙ ⠞⠓⠑ ⠉⠁⠎⠑ ⠁⠝⠙ ⠗⠥⠇⠑⠙ ⠊⠝ ⠓⠑⠗ ⠋⠁⠧⠕⠗ ⠠⠞⠑⠭⠁⠎ ⠞⠓⠑⠝ ⠁⠏⠏⠑⠁⠇⠑⠙ ⠞⠓⠊⠎ ⠗⠥⠇⠊⠝⠛ ⠙⠊⠗⠑⠉⠞⠇⠽ ⠞⠕ ⠞⠓⠑ ⠠⠥⠠⠎ ⠠⠎⠥⠏⠗⠑⠍⠑ ⠠⠉⠕⠥⠗⠞⠠⠊⠝ ⠠⠚⠁⠝⠥⠁⠗⠽ ⠼⠁⠊⠛⠉ ⠞⠓⠑ ⠠⠎⠥⠏⠗⠑⠍⠑ ⠠⠉⠕⠥⠗⠞ ⠊⠎⠎⠥⠑⠙ ⠁ ⠼⠛⠼⠃ ⠙⠑⠉⠊⠎⠊⠕⠝ ⠊⠝ ⠠⠍⠉⠠⠉⠕⠗⠧⠑⠽⠎ ⠋⠁⠧⠕⠗ ⠗⠥⠇⠊⠝⠛ ⠞⠓⠁⠞ ⠞⠓⠑ ⠠⠙⠥⠑ ⠠⠏⠗⠕⠉⠑⠎⠎ ⠠⠉⠇⠁⠥⠎⠑ ⠕⠋ ⠞⠓⠑ ⠠⠋⠕⠥⠗⠞⠑⠑⠝⠞⠓ ⠠⠁⠍⠑⠝⠙⠍⠑⠝⠞ ⠞⠕ ⠞⠓⠑ ⠠⠥⠝⠊⠞⠑⠙ ⠠⠎⠞⠁⠞⠑⠎ ⠠⠉⠕⠝⠎⠞⠊⠞⠥⠞⠊⠕⠝ ⠏⠗⠕⠧⠊⠙⠑⠎ ⠁ ⠋⠥⠝⠙⠁⠍⠑⠝⠞⠁⠇ ⠗⠊⠛⠓⠞ ⠞⠕ ⠏⠗⠊⠧⠁⠉⠽ ⠺⠓⠊⠉⠓ ⠏⠗⠕⠞⠑⠉⠞⠎ ⠁ ⠏⠗⠑⠛⠝⠁⠝⠞ ⠺⠕⠍⠁⠝⠎ ⠗⠊⠛⠓⠞ ⠞⠕ ⠁⠝ ⠁⠃⠕⠗⠞⠊⠕⠝ ⠠⠃⠥⠞ ⠞⠓⠑ ⠠⠉⠕⠥⠗⠞ ⠁⠇⠎⠕ ⠓⠑⠇⠙ ⠞⠓⠁⠞ ⠞⠓⠑ ⠗⠊⠛⠓⠞ ⠞⠕ ⠁⠃⠕⠗⠞⠊⠕⠝ ⠊⠎ ⠝⠕⠞ ⠁⠃⠎⠕⠇⠥⠞⠑ ⠁⠝⠙ ⠍⠥⠎⠞ ⠃⠑ ⠃⠁⠇⠁⠝⠉⠑⠙ ⠁⠛⠁⠊⠝⠎⠞ ⠞⠓⠑ ⠛⠕⠧⠑⠗⠝⠍⠑⠝⠞⠎ ⠊⠝⠞⠑⠗⠑⠎⠞⠎ ⠊⠝ ⠏⠗⠕⠞⠑⠉⠞⠊⠝⠛ ⠺⠕⠍⠑⠝⠎ ⠓⠑⠁⠇⠞⠓ ⠁⠝⠙ ⠏⠗⠑⠝⠁⠞⠁⠇ ⠇⠊⠋⠑ ⠠⠞⠓⠑ ⠠⠉⠕⠥⠗⠞ ⠗⠑⠎⠕⠇⠧⠑⠙ ⠞⠓⠑⠎⠑ ⠉⠕⠍⠏⠑⠞⠊⠝⠛ ⠊⠝⠞⠑⠗⠑⠎⠞⠎ ⠃⠽ ⠁⠝⠝⠕⠥⠝⠉⠊⠝⠛ ⠁ ⠞⠗⠊⠍⠑⠎⠞⠑⠗ ⠞⠊⠍⠑⠞⠁⠃⠇⠑ ⠞⠕ ⠛⠕⠧⠑⠗⠝ ⠁⠇⠇ ⠁⠃⠕⠗⠞⠊⠕⠝ ⠗⠑⠛⠥⠇⠁⠞⠊⠕⠝⠎ ⠊⠝ ⠞⠓⠑ ⠠⠥⠝⠊⠞⠑⠙ ⠠⠎⠞⠁⠞⠑⠎ ⠠⠞⠓⠑ ⠠⠉⠕⠥⠗⠞ ⠁⠇⠎⠕ ⠉⠇⠁⠎⠎⠊⠋⠊⠑⠙ ⠞⠓⠑ ⠗⠊⠛⠓⠞ ⠞⠕ ⠁⠃⠕⠗⠞⠊⠕⠝ ⠁⠎ ⠋⠥⠝⠙⠁⠍⠑⠝⠞⠁⠇ ⠺⠓⠊⠉⠓ ⠗⠑⠟⠥⠊⠗⠑⠙ ⠉⠕⠥⠗⠞⠎ ⠞⠕ ⠑⠧⠁⠇⠥⠁⠞⠑ ⠉⠓⠁⠇⠇⠑⠝⠛⠑⠙ ⠁⠃⠕⠗⠞⠊⠕⠝ ⠇⠁⠺⠎ ⠥⠝⠙⠑⠗ ⠞⠓⠑ ⠎⠞⠗⠊⠉⠞ ⠎⠉⠗⠥⠞⠊⠝⠽ ⠎⠞⠁⠝⠙⠁⠗⠙ ⠞⠓⠑ ⠍⠕⠎⠞ ⠎⠞⠗⠊⠝⠛⠑⠝⠞ ⠇⠑⠧⠑⠇ ⠕⠋ ⠚⠥⠙⠊⠉⠊⠁⠇ ⠗⠑⠧⠊⠑⠺ ⠊⠝ ⠞⠓⠑ ⠠⠥⠝⠊⠞⠑⠙ ⠠⠎⠞⠁⠞⠑⠎",
      "compressed": {
        "compressed": "11111111",
        "metadata": {
          "originalSize": 17064,
          "compressedSize": 8,
          "compressionRatio": 0.00046882325363338024,
          "compressionPercentage": "99.95%",
          "processingTime": "0.02ms",
          "conceptCount": 1,
          "encodingType": "semantic"
        },
        "compressionMap": {
          "STRING": "11111111"
        }
      },
      "path": "/home/owner/CascadeProjects/braille/data/legal/cases/roe_v_wade.json"
    }
  },
  "statutes": {
    "first_amendment": {
      "id": "first_amendment",
      "title": "First Amendment to the United States Constitution",
      "jurisdiction": "United States",
      "year": "1791",
      "section": "Bill of Rights",
      "concepts": [
        "constitutional_law",
        "freedom_of_speech",
        "freedom_of_religion",
        "freedom_of_assembly"
      ],
      "citations": [],
      "bbesEncoding": "⠠⠋⠊⠗⠎⠞ ⠠⠁⠍⠑⠝⠙⠍⠑⠝⠞ ⠞⠕ ⠞⠓⠑ ⠠⠥⠝⠊⠞⠑⠙ ⠠⠎⠞⠁⠞⠑⠎ ⠠⠉⠕⠝⠎⠞⠊⠞⠥⠞⠊⠕⠝⠠⠉⠕⠝⠛⠗⠑⠎⠎ ⠎⠓⠁⠇⠇ ⠍⠁⠅⠑ ⠝⠕ ⠇⠁⠺ ⠗⠑⠎⠏⠑⠉⠞⠊⠝⠛ ⠁⠝ ⠑⠎⠞⠁⠃⠇⠊⠎⠓⠍⠑⠝⠞ ⠕⠋ ⠗⠑⠇⠊⠛⠊⠕⠝ ⠕⠗ ⠏⠗⠕⠓⠊⠃⠊⠞⠊⠝⠛ ⠞⠓⠑ ⠋⠗⠑⠑ ⠑⠭⠑⠗⠉⠊⠎⠑ ⠞⠓⠑⠗⠑⠕⠋ ⠕⠗ ⠁⠃⠗⠊⠙⠛⠊⠝⠛ ⠞⠓⠑ ⠋⠗⠑⠑⠙⠕⠍ ⠕⠋ ⠎⠏⠑⠑⠉⠓ ⠕⠗ ⠕⠋ ⠞⠓⠑ ⠏⠗⠑⠎⠎ ⠕⠗ ⠞⠓⠑ ⠗⠊⠛⠓⠞ ⠕⠋ ⠞⠓⠑ ⠏⠑⠕⠏⠇⠑ ⠏⠑⠁⠉⠑⠁⠃⠇⠽ ⠞⠕ ⠁⠎⠎⠑⠍⠃⠇⠑ ⠁⠝⠙ ⠞⠕ ⠏⠑⠞⠊⠞⠊⠕⠝ ⠞⠓⠑ ⠠⠛⠕⠧⠑⠗⠝⠍⠑⠝⠞ ⠋⠕⠗ ⠁ ⠗⠑⠙⠗⠑⠎⠎ ⠕⠋ ⠛⠗⠊⠑⠧⠁⠝⠉⠑⠎⠠⠞⠓⠑ ⠠⠋⠊⠗⠎⠞ ⠠⠁⠍⠑⠝⠙⠍⠑⠝⠞ ⠺⠁⠎ ⠁⠙⠕⠏⠞⠑⠙ ⠕⠝ ⠠⠙⠑⠉⠑⠍⠃⠑⠗ ⠼⠁⠑ ⠼⠁⠛⠊⠁ ⠁⠎ ⠕⠝⠑ ⠕⠋ ⠞⠓⠑ ⠞⠑⠝ ⠁⠍⠑⠝⠙⠍⠑⠝⠞⠎ ⠞⠓⠁⠞ ⠉⠕⠝⠎⠞⠊⠞⠥⠞⠑ ⠞⠓⠑ ⠠⠃⠊⠇⠇ ⠕⠋ ⠠⠗⠊⠛⠓⠞⠎ ⠠⠞⠓⠑ ⠠⠋⠊⠗⠎⠞ ⠠⠁⠍⠑⠝⠙⠍⠑⠝⠞ ⠏⠗⠕⠓⠊⠃⠊⠞⠎ ⠠⠉⠕⠝⠛⠗⠑⠎⠎ ⠋⠗⠕⠍ ⠍⠁⠅⠊⠝⠛ ⠁⠝⠽ ⠇⠁⠺ ⠗⠑⠎⠏⠑⠉⠞⠊⠝⠛ ⠁⠝ ⠑⠎⠞⠁⠃⠇⠊⠎⠓⠍⠑⠝⠞ ⠕⠋ ⠗⠑⠇⠊⠛⠊⠕⠝ ⠏⠗⠕⠓⠊⠃⠊⠞⠊⠝⠛ ⠞⠓⠑ ⠋⠗⠑⠑ ⠑⠭⠑⠗⠉⠊⠎⠑ ⠕⠋ ⠗⠑⠇⠊⠛⠊⠕⠝ ⠕⠗ ⠁⠃⠗⠊⠙⠛⠊⠝⠛ ⠞⠓⠑ ⠋⠗⠑⠑⠙⠕⠍ ⠕⠋ ⠎⠏⠑⠑⠉⠓ ⠞⠓⠑ ⠋⠗⠑⠑⠙⠕⠍ ⠕⠋ ⠞⠓⠑ ⠏⠗⠑⠎⠎ ⠞⠓⠑ ⠋⠗⠑⠑⠙⠕⠍ ⠕⠋ ⠁⠎⠎⠑⠍⠃⠇⠽ ⠕⠗ ⠞⠓⠑ ⠗⠊⠛⠓⠞ ⠞⠕ ⠏⠑⠞⠊⠞⠊⠕⠝ ⠞⠓⠑ ⠛⠕⠧⠑⠗⠝⠍⠑⠝⠞ ⠋⠕⠗ ⠁ ⠗⠑⠙⠗⠑⠎⠎ ⠕⠋ ⠛⠗⠊⠑⠧⠁⠝⠉⠑⠎⠠⠞⠓⠑ ⠠⠋⠊⠗⠎⠞ ⠠⠁⠍⠑⠝⠙⠍⠑⠝⠞ ⠓⠁⠎ ⠃⠑⠑⠝ ⠊⠝⠞⠑⠗⠏⠗⠑⠞⠑⠙ ⠃⠽ ⠞⠓⠑ ⠠⠎⠥⠏⠗⠑⠍⠑ ⠠⠉⠕⠥⠗⠞ ⠁⠎ ⠁⠏⠏⠇⠽⠊⠝⠛ ⠞⠕ ⠞⠓⠑ ⠑⠝⠞⠊⠗⠑ ⠋⠑⠙⠑⠗⠁⠇ ⠛⠕⠧⠑⠗⠝⠍⠑⠝⠞ ⠑⠧⠑⠝ ⠞⠓⠕⠥⠛⠓ ⠊⠞ ⠊⠎ ⠕⠝⠇⠽ ⠑⠭⠏⠗⠑⠎⠎⠇⠽ ⠁⠏⠏⠇⠊⠉⠁⠃⠇⠑ ⠞⠕ ⠠⠉⠕⠝⠛⠗⠑⠎⠎ ⠠⠋⠥⠗⠞⠓⠑⠗⠍⠕⠗⠑ ⠞⠓⠑ ⠠⠉⠕⠥⠗⠞ ⠓⠁⠎ ⠊⠝⠞⠑⠗⠏⠗⠑⠞⠑⠙ ⠞⠓⠑ ⠠⠙⠥⠑ ⠠⠏⠗⠕⠉⠑⠎⠎ ⠠⠉⠇⠁⠥⠎⠑ ⠕⠋ ⠞⠓⠑ ⠠⠋⠕⠥⠗⠞⠑⠑⠝⠞⠓ ⠠⠁⠍⠑⠝⠙⠍⠑⠝⠞ ⠁⠎ ⠏⠗⠕⠞⠑⠉⠞⠊⠝⠛ ⠞⠓⠑ ⠗⠊⠛⠓⠞⠎ ⠊⠝ ⠞⠓⠑ ⠠⠋⠊⠗⠎⠞ ⠠⠁⠍⠑⠝⠙⠍⠑⠝⠞ ⠋⠗⠕⠍ ⠊⠝⠞⠑⠗⠋⠑⠗⠑⠝⠉⠑ ⠃⠽ ⠎⠞⠁⠞⠑ ⠛⠕⠧⠑⠗⠝⠍⠑⠝⠞⠎ ⠠⠞⠓⠑ ⠋⠗⠑⠑⠙⠕⠍ ⠕⠋ ⠎⠏⠑⠑⠉⠓ ⠞⠓⠑ ⠏⠗⠑⠎⠎ ⠁⠝⠙ ⠁⠎⠎⠑⠍⠃⠇⠽ ⠓⠁⠧⠑ ⠃⠑⠑⠝ ⠧⠊⠑⠺⠑⠙ ⠁⠎ ⠊⠝⠓⠑⠗⠑⠝⠞⠇⠽ ⠏⠕⠇⠊⠞⠊⠉⠁⠇ ⠊⠝ ⠝⠁⠞⠥⠗⠑ ⠃⠑⠊⠝⠛ ⠑⠎⠎⠑⠝⠞⠊⠁⠇ ⠞⠕ ⠞⠓⠑ ⠙⠑⠍⠕⠉⠗⠁⠞⠊⠉ ⠏⠗⠕⠉⠑⠎⠎",
      "compressed": {
        "compressed": "11111111",
        "metadata": {
          "originalSize": 9880,
          "compressedSize": 8,
          "compressionRatio": 0.0008097165991902834,
          "compressionPercentage": "99.92%",
          "processingTime": "0.01ms",
          "conceptCount": 1,
          "encodingType": "semantic"
        },
        "compressionMap": {
          "STRING": "11111111"
        }
      },
      "path": "/home/owner/CascadeProjects/braille/data/legal/statutes/first_amendment.json"
    },
    "fourth_amendment": {
      "id": "fourth_amendment",
      "title": "Fourth Amendment to the United States Constitution",
      "jurisdiction": "United States",
      "year": "1791",
      "section": "Bill of Rights",
      "concepts": [
        "constitutional_law",
        "search_and_seizure",
        "privacy",
        "probable_cause"
      ],
      "citations": [],
      "bbesEncoding": "⠠⠋⠕⠥⠗⠞⠓ ⠠⠁⠍⠑⠝⠙⠍⠑⠝⠞ ⠞⠕ ⠞⠓⠑ ⠠⠥⠝⠊⠞⠑⠙ ⠠⠎⠞⠁⠞⠑⠎ ⠠⠉⠕⠝⠎⠞⠊⠞⠥⠞⠊⠕⠝⠠⠞⠓⠑ ⠗⠊⠛⠓⠞ ⠕⠋ ⠞⠓⠑ ⠏⠑⠕⠏⠇⠑ ⠞⠕ ⠃⠑ ⠎⠑⠉⠥⠗⠑ ⠊⠝ ⠞⠓⠑⠊⠗ ⠏⠑⠗⠎⠕⠝⠎ ⠓⠕⠥⠎⠑⠎ ⠏⠁⠏⠑⠗⠎ ⠁⠝⠙ ⠑⠋⠋⠑⠉⠞⠎ ⠁⠛⠁⠊⠝⠎⠞ ⠥⠝⠗⠑⠁⠎⠕⠝⠁⠃⠇⠑ ⠎⠑⠁⠗⠉⠓⠑⠎ ⠁⠝⠙ ⠎⠑⠊⠵⠥⠗⠑⠎ ⠎⠓⠁⠇⠇ ⠝⠕⠞ ⠃⠑ ⠧⠊⠕⠇⠁⠞⠑⠙ ⠁⠝⠙ ⠝⠕ ⠠⠺⠁⠗⠗⠁⠝⠞⠎ ⠎⠓⠁⠇⠇ ⠊⠎⠎⠥⠑ ⠃⠥⠞ ⠥⠏⠕⠝ ⠏⠗⠕⠃⠁⠃⠇⠑ ⠉⠁⠥⠎⠑ ⠎⠥⠏⠏⠕⠗⠞⠑⠙ ⠃⠽ ⠠⠕⠁⠞⠓ ⠕⠗ ⠁⠋⠋⠊⠗⠍⠁⠞⠊⠕⠝ ⠁⠝⠙ ⠏⠁⠗⠞⠊⠉⠥⠇⠁⠗⠇⠽ ⠙⠑⠎⠉⠗⠊⠃⠊⠝⠛ ⠞⠓⠑ ⠏⠇⠁⠉⠑ ⠞⠕ ⠃⠑ ⠎⠑⠁⠗⠉⠓⠑⠙ ⠁⠝⠙ ⠞⠓⠑ ⠏⠑⠗⠎⠕⠝⠎ ⠕⠗ ⠞⠓⠊⠝⠛⠎ ⠞⠕ ⠃⠑ ⠎⠑⠊⠵⠑⠙⠠⠞⠓⠑ ⠠⠋⠕⠥⠗⠞⠓ ⠠⠁⠍⠑⠝⠙⠍⠑⠝⠞ ⠺⠁⠎ ⠁⠙⠕⠏⠞⠑⠙ ⠕⠝ ⠠⠙⠑⠉⠑⠍⠃⠑⠗ ⠼⠁⠑ ⠼⠁⠛⠊⠁ ⠁⠎ ⠏⠁⠗⠞ ⠕⠋ ⠞⠓⠑ ⠠⠃⠊⠇⠇ ⠕⠋ ⠠⠗⠊⠛⠓⠞⠎ ⠠⠞⠓⠑ ⠠⠋⠕⠥⠗⠞⠓ ⠠⠁⠍⠑⠝⠙⠍⠑⠝⠞ ⠏⠗⠕⠓⠊⠃⠊⠞⠎ ⠥⠝⠗⠑⠁⠎⠕⠝⠁⠃⠇⠑ ⠎⠑⠁⠗⠉⠓⠑⠎ ⠁⠝⠙ ⠎⠑⠊⠵⠥⠗⠑⠎ ⠁⠝⠙ ⠗⠑⠟⠥⠊⠗⠑⠎ ⠁⠝⠽ ⠺⠁⠗⠗⠁⠝⠞ ⠞⠕ ⠃⠑ ⠚⠥⠙⠊⠉⠊⠁⠇⠇⠽ ⠎⠁⠝⠉⠞⠊⠕⠝⠑⠙ ⠁⠝⠙ ⠎⠥⠏⠏⠕⠗⠞⠑⠙ ⠃⠽ ⠏⠗⠕⠃⠁⠃⠇⠑ ⠉⠁⠥⠎⠑ ⠠⠊⠞ ⠊⠎ ⠋⠥⠝⠙⠁⠍⠑⠝⠞⠁⠇ ⠞⠕ ⠠⠥⠠⠎ ⠉⠗⠊⠍⠊⠝⠁⠇ ⠏⠗⠕⠉⠑⠙⠥⠗⠑ ⠊⠝ ⠎⠑⠞⠞⠊⠝⠛ ⠞⠓⠑ ⠞⠑⠗⠍⠎ ⠥⠝⠙⠑⠗ ⠺⠓⠊⠉⠓ ⠛⠕⠧⠑⠗⠝⠍⠑⠝⠞ ⠁⠥⠞⠓⠕⠗⠊⠞⠊⠑⠎ ⠍⠁⠽ ⠉⠕⠝⠙⠥⠉⠞ ⠎⠑⠁⠗⠉⠓⠑⠎ ⠁⠝⠙ ⠎⠑⠊⠵⠥⠗⠑⠎ ⠕⠋ ⠏⠑⠗⠎⠕⠝⠎ ⠞⠓⠑⠊⠗ ⠏⠗⠕⠏⠑⠗⠞⠽ ⠁⠝⠙ ⠞⠓⠑⠊⠗ ⠓⠕⠍⠑⠎⠠⠞⠓⠑ ⠠⠎⠥⠏⠗⠑⠍⠑ ⠠⠉⠕⠥⠗⠞ ⠓⠁⠎ ⠊⠝⠞⠑⠗⠏⠗⠑⠞⠑⠙ ⠞⠓⠑ ⠠⠋⠕⠥⠗⠞⠓ ⠠⠁⠍⠑⠝⠙⠍⠑⠝⠞ ⠁⠎ ⠏⠗⠕⠧⠊⠙⠊⠝⠛ ⠏⠗⠕⠞⠑⠉⠞⠊⠕⠝ ⠁⠛⠁⠊⠝⠎⠞ ⠎⠑⠁⠗⠉⠓⠑⠎ ⠁⠝⠙ ⠎⠑⠊⠵⠥⠗⠑⠎ ⠉⠕⠝⠙⠥⠉⠞⠑⠙ ⠃⠽ ⠛⠕⠧⠑⠗⠝⠍⠑⠝⠞ ⠕⠋⠋⠊⠉⠊⠁⠇⠎ ⠞⠓⠁⠞ ⠁⠗⠑ ⠙⠑⠑⠍⠑⠙ ⠥⠝⠗⠑⠁⠎⠕⠝⠁⠃⠇⠑ ⠥⠝⠙⠑⠗ ⠞⠓⠑ ⠇⠁⠺ ⠠⠞⠓⠑ ⠠⠋⠕⠥⠗⠞⠓ ⠠⠁⠍⠑⠝⠙⠍⠑⠝⠞ ⠊⠎ ⠝⠕⠞ ⠁ ⠛⠥⠁⠗⠁⠝⠞⠑⠑ ⠁⠛⠁⠊⠝⠎⠞ ⠁⠇⠇ ⠎⠑⠁⠗⠉⠓⠑⠎ ⠁⠝⠙ ⠎⠑⠊⠵⠥⠗⠑⠎ ⠃⠥⠞ ⠕⠝⠇⠽ ⠞⠓⠕⠎⠑ ⠞⠓⠁⠞ ⠁⠗⠑ ⠙⠑⠑⠍⠑⠙ ⠥⠝⠗⠑⠁⠎⠕⠝⠁⠃⠇⠑ ⠥⠝⠙⠑⠗ ⠞⠓⠑ ⠇⠁⠺ ⠠⠺⠓⠑⠞⠓⠑⠗ ⠁ ⠏⠁⠗⠞⠊⠉⠥⠇⠁⠗ ⠎⠑⠁⠗⠉⠓ ⠕⠗ ⠎⠑⠊⠵⠥⠗⠑ ⠊⠎ ⠉⠕⠝⠎⠊⠙⠑⠗⠑⠙ ⠗⠑⠁⠎⠕⠝⠁⠃⠇⠑ ⠊⠎ ⠙⠑⠞⠑⠗⠍⠊⠝⠑⠙ ⠃⠽ ⠃⠁⠇⠁⠝⠉⠊⠝⠛ ⠞⠓⠑ ⠊⠝⠞⠗⠥⠎⠊⠕⠝ ⠕⠝ ⠁⠝ ⠊⠝⠙⠊⠧⠊⠙⠥⠁⠇⠎ ⠠⠋⠕⠥⠗⠞⠓ ⠠⠁⠍⠑⠝⠙⠍⠑⠝⠞ ⠗⠊⠛⠓⠞⠎ ⠁⠛⠁⠊⠝⠎⠞ ⠞⠓⠑ ⠛⠕⠧⠑⠗⠝⠍⠑⠝⠞⠎ ⠇⠑⠛⠊⠞⠊⠍⠁⠞⠑ ⠊⠝⠞⠑⠗⠑⠎⠞⠎ ⠎⠥⠉⠓ ⠁⠎ ⠏⠥⠃⠇⠊⠉ ⠎⠁⠋⠑⠞⠽",
      "compressed": {
        "compressed": "11111111",
        "metadata": {
          "originalSize": 10808,
          "compressedSize": 8,
          "compressionRatio": 0.0007401924500370096,
          "compressionPercentage": "99.93%",
          "processingTime": "0.02ms",
          "conceptCount": 1,
          "encodingType": "semantic"
        },
        "compressionMap": {
          "STRING": "11111111"
        }
      },
      "path": "/home/owner/CascadeProjects/braille/data/legal/statutes/fourth_amendment.json"
    }
  },
  "concepts": {
    "constitutional_law": {
      "cases": [
        "brown_v_board",
        "miranda_v_arizona",
        "roe_v_wade"
      ],
      "statutes": [
        "first_amendment",
        "fourth_amendment"
      ]
    },
    "civil_rights": {
      "cases": [
        "brown_v_board"
      ],
      "statutes": []
    },
    "equal_protection": {
      "cases": [
        "brown_v_board"
      ],
      "statutes": []
    },
    "criminal_law": {
      "cases": [
        "miranda_v_arizona"
      ],
      "statutes": []
    },
    "procedural_law": {
      "cases": [
        "miranda_v_arizona"
      ],
      "statutes": []
    },
    "fifth_amendment": {
      "cases": [
        "miranda_v_arizona"
      ],
      "statutes": []
    },
    "privacy": {
      "cases": [
        "roe_v_wade"
      ],
      "statutes": [
        "fourth_amendment"
      ]
    },
    "due_process": {
      "cases": [
        "roe_v_wade"
      ],
      "statutes": []
    },
    "freedom_of_speech": {
      "cases": [],
      "statutes": [
        "first_amendment"
      ]
    },
    "freedom_of_religion": {
      "cases": [],
      "statutes": [
        "first_amendment"
      ]
    },
    "freedom_of_assembly": {
      "cases": [],
      "statutes": [
        "first_amendment"
      ]
    },
    "search_and_seizure": {
      "cases": [],
      "statutes": [
        "fourth_amendment"
      ]
    },
    "probable_cause": {
      "cases": [],
      "statutes": [
        "fourth_amendment"
      ]
    }
  },
  "citations": {
    "brown_v_board": {
      "cites": [
        "Plessy v. Ferguson"
      ],
      "citedBy": []
    },
    "miranda_v_arizona": {
      "cites": [
        "Escobedo v. Illinois",
        "Gideon v. Wainwright"
      ],
      "citedBy": []
    },
    "roe_v_wade": {
      "cites": [
        "Griswold v. Connecticut",
        "Doe v. Bolton"
      ],
      "citedBy": []
    }
  },
  "lastUpdated": "2025-03-13T01:48:33.001Z"
}